mediate/__init__.py
mediate/decorators.py
mediate/middleware.py
mediate/partial.py
mediate/protocols.py
mediate/py.typed
mediate/typing.py
mediate-0.1.6.dist-info/LICENSE
mediate-0.1.6.dist-info/WHEEL
mediate-0.1.6.dist-info/METADATA
mediate-0.1.6.dist-info/RECORD
