Metadata-Version: 2.1
Name: mediate
Version: 0.1.6
Summary: Middleware for every occasion
Home-page: https://github.com/tombulled/middleware
License: MIT
Keywords: python,middleware,mediate
Author: Tom Bulled
Author-email: 26026015+tombulled@users.noreply.github.com
Requires-Python: >=3.8,<4.0
Classifier: License :: OSI Approved :: MIT License
Classifier: Programming Language :: Python :: 3
Classifier: Programming Language :: Python :: 3.8
Classifier: Programming Language :: Python :: 3.9
Classifier: Programming Language :: Python :: 3.10
Classifier: Programming Language :: Python :: 3.11
Requires-Dist: roster (>=0.1.11,<0.2.0)
Requires-Dist: typing-extensions (>=4.4.0,<5.0.0)
Project-URL: Documentation, https://github.com/tombulled/middleware
Project-URL: Repository, https://github.com/tombulled/middleware
